assets/__init__.py
assets/images/__init__.py
assets/images/favicon.ico
assets/images/govuk-crest.png
assets/images/logo.svg
assets/javascripts/__init__.py
assets/javascripts/bundle.js
assets/javascripts/lunr/__init__.py
assets/javascripts/lunr/tinyseg.js
assets/javascripts/lunr/wordcut.js
assets/javascripts/lunr/min/__init__.py
assets/javascripts/lunr/min/lunr.ar.min.js
assets/javascripts/lunr/min/lunr.da.min.js
assets/javascripts/lunr/min/lunr.de.min.js
assets/javascripts/lunr/min/lunr.du.min.js
assets/javascripts/lunr/min/lunr.el.min.js
assets/javascripts/lunr/min/lunr.es.min.js
assets/javascripts/lunr/min/lunr.fi.min.js
assets/javascripts/lunr/min/lunr.fr.min.js
assets/javascripts/lunr/min/lunr.he.min.js
assets/javascripts/lunr/min/lunr.hi.min.js
assets/javascripts/lunr/min/lunr.hu.min.js
assets/javascripts/lunr/min/lunr.hy.min.js
assets/javascripts/lunr/min/lunr.it.min.js
assets/javascripts/lunr/min/lunr.ja.min.js
assets/javascripts/lunr/min/lunr.jp.min.js
assets/javascripts/lunr/min/lunr.kn.min.js
assets/javascripts/lunr/min/lunr.ko.min.js
assets/javascripts/lunr/min/lunr.multi.min.js
assets/javascripts/lunr/min/lunr.nl.min.js
assets/javascripts/lunr/min/lunr.no.min.js
assets/javascripts/lunr/min/lunr.pt.min.js
assets/javascripts/lunr/min/lunr.ro.min.js
assets/javascripts/lunr/min/lunr.ru.min.js
assets/javascripts/lunr/min/lunr.sa.min.js
assets/javascripts/lunr/min/lunr.stemmer.support.min.js
assets/javascripts/lunr/min/lunr.sv.min.js
assets/javascripts/lunr/min/lunr.ta.min.js
assets/javascripts/lunr/min/lunr.te.min.js
assets/javascripts/lunr/min/lunr.th.min.js
assets/javascripts/lunr/min/lunr.tr.min.js
assets/javascripts/lunr/min/lunr.vi.min.js
assets/javascripts/lunr/min/lunr.zh.min.js
assets/javascripts/workers/__init__.py
assets/javascripts/workers/search.js
assets/stylesheets/__init__.py
assets/stylesheets/main.css
extensions/__init__.py
extensions/emoji.py
partials/__init__.py
partials/actions.html
partials/alternate.html
partials/comments.html
ons_mkdocs_theme-0.2.8.dist-info/LICENSE
ons_mkdocs_theme-0.2.8.dist-info/METADATA
ons_mkdocs_theme-0.2.8.dist-info/WHEEL
ons_mkdocs_theme-0.2.8.dist-info/entry_points.txt
ons_mkdocs_theme-0.2.8.dist-info/top_level.txt
ons_mkdocs_theme-0.2.8.dist-info/RECORD
