Metadata-Version: 2.1
Name: ons-mkdocs-theme
Version: 0.2.8
Summary: An ONS theme for MkDocs based on Material for MkDocs
Home-page: https://github.com/ONSdigital/ons-mkdocs-theme
Author: Keilan Evans, ONS
Author-email: Keilan.Evans@ons.gov.uk
Classifier: Programming Language :: Python :: 3.11
Classifier: License :: OSI Approved :: MIT License
Classifier: Operating System :: OS Independent
Requires-Python: <3.12,>=3.11
License-File: LICENSE
Requires-Dist: Babel ==2.15.0
Requires-Dist: certifi ==2024.7.4
Requires-Dist: charset-normalizer ==3.3.2
Requires-Dist: click ==8.1.7
Requires-Dist: colorama ==0.4.6
Requires-Dist: csscompressor ==0.9.5
Requires-Dist: ghp-import ==2.1.0
Requires-Dist: htmlmin2 ==0.1.13
Requires-Dist: idna ==3.7
Requires-Dist: Jinja2 ==3.1.4
Requires-Dist: jsmin ==3.0.1
Requires-Dist: Markdown ==3.6
Requires-Dist: MarkupSafe ==2.1.5
Requires-Dist: mergedeep ==1.3.4
Requires-Dist: mkdocs ==1.6.0
Requires-Dist: mkdocs-get-deps ==0.2.0
Requires-Dist: mkdocs-material ==9.5.30
Requires-Dist: mkdocs-material-extensions ==1.3.1
Requires-Dist: mkdocs-minify-plugin ==0.8.0
Requires-Dist: packaging ==24.1
Requires-Dist: paginate ==0.5.6
Requires-Dist: pathspec ==0.12.1
Requires-Dist: platformdirs ==4.2.2
Requires-Dist: Pygments ==2.18.0
Requires-Dist: pymdown-extensions ==10.9
Requires-Dist: python-dateutil ==2.9.0.post0
Requires-Dist: PyYAML ==6.0.1
Requires-Dist: pyyaml-env-tag ==0.1
Requires-Dist: regex ==2024.7.24
Requires-Dist: requests ==2.32.3
Requires-Dist: six ==1.16.0
Requires-Dist: urllib3 ==2.2.2
Requires-Dist: watchdog ==4.0.1
